gitlogparser/__init__.py
gitlogparser/main.py
gitlogparser/models.py
gitlogparser/parser.py
gitlogparser/stats.py
tests/__init__.py
tests/test_gitLogParser.py
gitlogparser-0.1.6.dist-info/METADATA
gitlogparser-0.1.6.dist-info/WHEEL
gitlogparser-0.1.6.dist-info/entry_points.txt
gitlogparser-0.1.6.dist-info/top_level.txt
gitlogparser-0.1.6.dist-info/RECORD
