Metadata-Version: 2.1
Name: gitlogparser
Version: 0.1.6
Summary: Parser for 'git log' command
Home-page: https://github.com/gaborantal/git-log-parser
Author: Gabor Antal
Author-email: antalgabor1993@gmail.com
License: UNKNOWN
Platform: UNKNOWN
Classifier: Programming Language :: Python :: 3
Classifier: Operating System :: OS Independent
Requires-Python: >=3.6
